l4l/__init__.py
l4l/base.py
l4l/file.py
l4l/formats.py
logs4thelazy-0.0.2.dist-info/LICENSE
logs4thelazy-0.0.2.dist-info/METADATA
logs4thelazy-0.0.2.dist-info/WHEEL
logs4thelazy-0.0.2.dist-info/top_level.txt
logs4thelazy-0.0.2.dist-info/RECORD
