Metadata-Version: 2.1
Name: logs4thelazy
Version: 0.0.2
Summary: A simple and easy to use library for logging in python
Home-page: https://github.com/FrostyTheSouthernSnowman/logging4thelazy
Download-URL: https://github.com/FrostyTheSouthernSnowman/logging4thelazy/archive/v_0.0.2.tar.gz
Author: Yosi Frost
Author-email: yosi_frost@icloud.com
License: MIT
Keywords: logging,python3,simple
Platform: UNKNOWN
Classifier: Development Status :: 4 - Beta
Classifier: Intended Audience :: Developers
Classifier: Topic :: Software Development :: Libraries
Classifier: License :: OSI Approved :: MIT License
Classifier: Programming Language :: Python :: 3
Classifier: Programming Language :: Python :: 3.4
Classifier: Programming Language :: Python :: 3.5
Classifier: Programming Language :: Python :: 3.6
Classifier: Programming Language :: Python :: 3.7
Classifier: Programming Language :: Python :: 3.8
Classifier: Programming Language :: Python :: 3.9
Classifier: Programming Language :: Python :: 3.10
License-File: LICENSE
